[
  {
    "file": "EXMU-X261_Datasheet.pdf",
    "path": "D:\\Innodisk\\Innodisk Product Selector\\IPA\\EP\\Computing\\AMD\\1. Datasheet\\EXMU-X261_Datasheet.pdf",
    "timestamp": "2026-06-03T10:40:54.464237",
    "status": "ok",
    "method": "rule_based",
    "confidence_score": 0.94,
    "warnings": [],
    "part_no": "EXMU-X261"
  },
  {
    "file": "EXOU-X261_Datasheet.pdf",
    "path": "D:\\Innodisk\\Innodisk Product Selector\\IPA\\EP\\Computing\\AMD\\1. Datasheet\\EXOU-X261_Datasheet.pdf",
    "timestamp": "2026-06-03T10:40:55.544050",
    "status": "ok",
    "method": "rule_based",
    "confidence_score": 0.94,
    "warnings": [],
    "part_no": "EXOU-X261"
  },
  {
    "file": "Datasheet_EXEC-Q911_DVT_20251218_Preliminary.pdf",
    "path": "D:\\Innodisk\\Innodisk Product Selector\\IPA\\EP\\Computing\\Qualcomm\\1. Datasheet\\EXEC-Q911\\Datasheet_EXEC-Q911_DVT_20251218_Preliminary.pdf",
    "timestamp": "2026-06-03T10:40:56.609413",
    "status": "ok",
    "method": "rule_based",
    "confidence_score": 1.0,
    "warnings": [],
    "part_no": "EXEC-Q911"
  },
  {
    "file": "Datasheet_EXMP-Q911_DVT_20260116_Preliminary.pdf",
    "path": "D:\\Innodisk\\Innodisk Product Selector\\IPA\\EP\\Computing\\Qualcomm\\1. Datasheet\\EXMP-Q911\\Datasheet_EXMP-Q911_DVT_20260116_Preliminary.pdf",
    "timestamp": "2026-06-03T10:40:57.723016",
    "status": "ok",
    "method": "rule_based",
    "confidence_score": 0.88,
    "warnings": [],
    "part_no": "EXMP-Q911"
  }
]